{
  "school_name": "香港大学",
  "major_name": "教育学硕士（数学教育）",
  "ename": "Master of Education (Mathematics Education)",
  "tags": "社科,教育,教育学院",
  "introduction": "专业方向: 教育\n入学时间: 9月\n项目时长: 1年\n项目学费: 229800港币/年",
  "requirements": "具有学士学位或同等学历",
  "objectives": "教育学硕士（数学教育）项目为直接参与数学教育的教师和其他教育工作者而设计。教育学硕士（数学教育）项目旨在从社会和文化背景、教学和学习、课程、哲学和技术的影响等多个角度提供一个全面的概述，涵盖了相关的研究和对该学科的贡献。",
  "language_requirements": "{{ per_lang.name }}",
  "curriculum": "教育问题与研究 (Educational Issues and Research)\n数学教与学研究 (Research into the Teaching and Learning of Mathematics)\n数学课程研究与开发 (Curriculum Research and Development in Mathematics)\n数学教学设计的创新与发展 (Innovation and Development of Instructional Design in Mathematics)\n数学教育的哲学、社会和文化层面 (The Philosophical, Social and Cultural Aspects of Mathematics Education)\n专业作品集或研究项目 (Professional Portfolio or Research Project)\n统计方法概论 (Introduction to Statistical Methods)\n定性方法:研究设计、数据收集和分析 (Qualitative Methods: Research Design, Data Collection and Analysis)\n教育中的叙事分析 (Narrative Analysis in Education)\n教育评价研究方法 (Methods for Evaluation Research in Education)\n心理测量原理与方法简介 (Introduction to Psychometric Principles and Methods)\n课程的比较视角 (Comparative Perspectives on Curriculum)\n英语文学和语言艺术 (Literature and Language Arts in English)\n书面话语 (Written Discourse)\n管理学校里的破坏性行为 (Managing Disruptive Behavior in School)",
  "success_cases": ""
}