{
  "school_name": "香港岭南大学",
  "major_name": "中国及区域发展研究硕士",
  "ename": "Master of China and Regional Development Studies",
  "tags": "社科,国际关系,研究生院",
  "introduction": "专业方向: 国际关系\n入学时间: 9月\n项目时长: 1年\n项目学费: 166000港币/年",
  "requirements": "- 持有大学认可的高等教育机构颁发的相关学士学位；或\n- 已获得同等学历；或\n- 能够提供令人满意的学术和专业成就证明。",
  "objectives": "中国的经济和地缘政治崛起已经成为学术讨论和研究的中心舞台。特别是，中国对亚太地区和非洲国家经济和政治事务的突出地位和兴趣，引起了多学科和多层次区域研究领域的研究人员和实践者的高度。在这些重要原因的背景下，岭南大学研究生院在其全球合作伙伴的支持下，成立了中国与区域研究文学硕士项目。\n香港岭南大学中国与区域研究文学硕士项目是一项高级比较区域研究，旨在让学生掌握知识和技能，以研究围绕中国与非洲国家及其亚太地区邻国交往的多方面理论和实证辩论，专为有志于拓展中国区域和全球关系知识的学者、评论员和公共和私营部门的实践者设计。",
  "language_requirements": "{{ per_lang.name }}",
  "curriculum": "国际关系理论与方法 (Theories and Approaches of International Relations)\n全球经济相互依存政治 (Politics of Global Economic Interdependence)\n比较政治学理论与方法 (Theories and Approaches of Comparative Politics)\n中非研究导论 (Introduction to China-Africa Studies)\n非洲和中国的宗教、文化与发展 (Religion, Culture and Development in Africa and China)\n国际中非研究专题讨论会（基于关于中非不同主题的年度专题讨论会） (International Symposium on Sino-African Studies (based on an annual symposium on varying themes on China-Africa) )\n中非关系：过去与现在 (China-Africa Relations: Past and Present)\n中非比较研究长论文 (Long Essay on Comparative China-Africa Studies)",
  "success_cases": ""
}