{
  "school_name": "香港岭南大学",
  "major_name": "融合科技理学硕士",
  "ename": "MSc Cross-disciplinary Technologies",
  "tags": "工科,计算机,研究生院",
  "introduction": "专业方向: 计算机\n入学时间: 9月\n项目时长: 1年\n项目学费: 188000港币/年",
  "requirements": "- 持有大学认可的高等教育机构颁发的相关学士学位；或\n- 已获得同等学历；或\n- 能够提供令人满意的学术和专业成就证明。",
  "objectives": "香港岭南大学融合科技理学硕士项目旨在为学生提供未来所需的核心知识和技能，包括：人工智能、计算机编程、先进制造、电子商务与国际电子商务、新媒体与管理、能源管理、财务与会计、企业管理与创新方面的知识和技能基础。",
  "language_requirements": "{{ per_lang.name }}",
  "curriculum": "计算机系统和编程基础 (Computer Systems and Programming Basics)\n数据分析和决策原理 (Principles of Data Analytics and Decision Making)\n控制系统和人工智能应用 (Control System and Artificial Intelligence Applications)\n产品和工艺设计与实施 (Product and Process Design and Implementation)\n项目管理：概念和工具 (Project Management: Concepts and Tools)\n技术专业人员的领导力和人际交往能力 (Leadership and Interpersonal Skills for Technology Professionals)\n材料、加工技术与设备 (Material, Processing Technology and Equipment)\n汽车制造 (Automobile Construction)\n现代电子商务 (Modern Electronic Business)\n供应链管理 (Supply Chain Management)\n新媒体和视频 (New Media and Video)\nSAAS与智能制造系统设计 (SAAS and Smart Manufacturing System Design)\n为技术专业人员建立商业思维 (Establish Business Mindset for Technology Professionals)\n经济与金融分析 (Economics and Financial Analysis)\n常规能源和可再生能源 (Conventional Energy and Renewable Energy)\n可持续城市能源规划 (Sustainable Urban Energy Planning)\n绿色金融与投资 (Green Finance and Investment)\n技术硕士实地考察 (Master of Technology Field Trip)\n技术硕士顶点项目 (Master of Technology Capstone Project)",
  "success_cases": ""
}