{
  "school_name": "香港城市大学",
  "major_name": "社会工作硕士",
  "ename": "Master of Social Work",
  "tags": "社科,社会学与社工,人文与社会科学学院",
  "introduction": "专业方向: 社会学与社工\n入学时间: 9月\n项目时长: 2年\n项目学费: 170500港币/年",
  "requirements": "具有学校认可的学士学位或同等学历，需要接受面试",
  "objectives": "香港城市大学社会工作硕士课程旨在培训专业人才达至以硕士课程获取的认可社会工作专业（注册社会工作者）。香港城市大学社会工作硕士课程期望培养学生成为伦理为本的社会工作者，得以胜任职务，在工作上表现良好的专业技能，展示良好的自我反思能力。\n学生修毕香港城市大学社会工作硕士课程后能够：运用适当的知识与理论，在社会工作范畴上实践所学技巧，得以胜任工作，表现专业；依据社会工作的价值和道德观念，反思自身的做法，明智地构建、表达和评价自己的理念和实践方法；以创新的方式，发挥统合理论与实践的能力，同时在不同文化的实践上发掘及探索相关的社会工作实务；评估专业活动、各种服务项目及不断在变的社会需求，倡导适当的福利改革和服务提供模式。",
  "language_requirements": "{{ per_lang.name }}",
  "curriculum": "社会福利政策体系与改革 (Social Welfare Policy System and Reform)\n社会福利服务管理 (Social Welfare Management)\n社会工作者相关的法律议题 (Legal Issues for the Social Worker)\n社会工作专业导论 (Social Work as a Profession)\n社会工作理论与实践I：个人和家庭 (Social Work Theories and Practice I: Working with Individuals and Families)\n社会工作理论与实践II：小组工作 (Social Work Theories and Practice II: Working with Groups  )\n社会工作理论与实践III：社区工作及宏观社会工作实务 (Social Work Theories and Practice III: Community Work and Marco-level Social Work Practice  )\n人类行为与多元性 (Human Behaviour and Diversity)\n社会工作研究方法 (Social Work Research Methods)\n实习相关工作坊 (Practicum Related Workshop )\n实习 (Fieldwork )\n社会工作综合小组讨论 (Integrative Social Work Seminar  )\n社会工作的社会科学理论 (Social Sciences Theories for Social Work)\n现代社会的社会问题 (Social Problems in Contemporary Societies)\n小组辅导与治疗 (Group Counselling and Therapy)",
  "success_cases": ""
}