{
  "school_name": "香港理工大学",
  "major_name": "中国文化文学硕士",
  "ename": "MA Chinese Culture",
  "tags": "社科,文化,人文学院",
  "introduction": "专业方向: 文化\n入学时间: 9月\n项目时长: 1年\n项目学费: 190500港币/年",
  "requirements": "具有认可院校颁发的学士学位，不限专业背景\n非汉语母语的学生需要具备良好的汉语知识\n个别情况下学院会根据个案考虑，申请者可能需要参加面试或笔试以进一步证明他们的语言能力",
  "objectives": "香港理工大学中国文化学系以弘扬古今学术，贯通中西文化为其宗旨。本系绝大多数之专任教授，均曾负笈于哈佛、普林斯顿、柏克莱、伦大、宾夕法尼亚、哥伦比亚等世界著名学府并取得博士学位，且多人为学术重镇，其专业成就深受学界的肯定和推崇。香港理工大学中国文化学系之教学，融中国文学、史学、哲学、宗教与艺术于一炉，不仅在香港高校人文学系中首创，在海峡两岸亦别具特色。\n香港理工大学中国文化学系开办的中国文化文学硕士课程，在香港各大学中堪称首创，在中国大陆、台湾、澳门乃至世界各地的高等院校中亦不多见。丰富而多样的科目，范围包括中国社会与文化、宗教与思想、文学与艺术、商业与文化旅游等。香港理工大学中国文化文学硕士课程教学的特点，除了系统性的方法学训练和基础知识的强化之外，还强调中国文学、史学、哲学、宗教和艺术的融会性、整合性及应用性的展现。学员除了修读必修的研究基础科目之外，还可因应个人兴趣及职业需要而自由选择科目，以期获得学习的最佳效果。香港理工大学中国文化文学硕士课程多由国际性很强的专家学者担任教授，能为爱好中国文化的人士提供高水平的学术知识，更能为教师以及从事中国商贸、外交、旅游业务和推广文化项目的人员提供丰富其个人文化素养、增强其事业能力的学识，故此值得特别推荐。\n香港理工大学中国文化文学硕士课程旨在：发展及提升学员中国文化的学养；加深学员对中国文化的理解；增强学员对中国文化的赏识；扩充学员中国文化古迹的知识；奠定学员从事中国文化相关研究及中国文化教学的基础。",
  "language_requirements": "{{ per_lang.name }}",
  "curriculum": "中国文化研究入门 (Introduction to the Study of Chinese Culture)\n中华文化考察 (Studying Chinese Culture through Fieldtrips)\n中国饮食文化 (Chinese Dietary Culture)\n中国风俗与礼仪  (Chinese Customs and Etiquettes )\n中国地下社会 (Underground Societies in China)\n民间信仰与术数方技  (Folk Beliefs and Occult Science )\n儒家思想与中国政教 (Government and Education in Confucianism)\n佛教与中国文化  (Buddhism and Chinese Culture )\n道教与中国文化 (Daoism and Chinese Culture)\n伊斯兰教、基督教与中国文化 (Islam, Christianity and Chinese Culture)\n中国文字的表达与应用 (The Expression and Application of Chinese Writing)\n中国韵文欣赏  (Appreciation of Chinese Classical Rhymed Writings)\n中国书画艺术欣赏 (Appreciation of Chinese Calligraphy and Paintings)\n中国传统舞台及说唱艺术 (Chinese Traditional Theatre and Performing Arts)\n中国商人与商业文化 (Businessmen and Business Culture in China)",
  "success_cases": ""
}