{
  "school_name": "东安格利亚大学",
  "major_name": "近代早期史文学硕士",
  "ename": "MA Early Modern History",
  "tags": "社科,历史,历史学院",
  "introduction": "专业方向: 历史\n入学时间: 9月\n项目时长: 1年\n项目学费: 22700英镑/年",
  "requirements": "具有英国2:1学士学位或同等学历，需要人文学科专业背景",
  "objectives": "东安格利亚大学近代早期史文学硕士项目以1500年至1750年间的英国、欧洲大陆和大西洋世界为重点，涵盖了各种各样的主题，包括宗教和政治、性别历史、权力和社会关系、心理、口述和印刷文化、真伪问题以及物质文化。我们课程的特点是学习的强度、严谨性和创造性。通过它，你不仅可以获得更深入、更先进的知识和对早期现代史的理解，而且还可以发展和提高对原始资料和文献所带来的问题和机遇的理解。您将学习如何应用复杂的历史理论和概念，以详细的例子和案例研究来检验假设。在讨论和工作中，你还将获得区分相互冲突的解释和观点的能力，并以清晰的方式讨论结果和交流。",
  "language_requirements": "{{ per_lang.name }}",
  "curriculum": "历史研究技能 (Historical Research Skills)\n近代早期社会、政治与文化 (Society, Politics and Culture in the Early Modern World)\n历史-专家教程 (History - Specialist Tutorials)\n硕士历史论文 (MA History Dissertation)\n英语古地理学 (English Paleography)",
  "success_cases": ""
}