{
  "school_name": "伦敦大学亚非学院",
  "major_name": "非洲研究文学硕士",
  "ename": "MA African Studies",
  "tags": "社科,国际关系,语言、文化和语言学学院",
  "introduction": "专业方向: 国际关系\n入学时间: 9月\n项目时长: 1年\n项目学费: 25320英镑/年",
  "requirements": "不限专业",
  "objectives": "伦敦大学亚非学院非洲研究文学硕士提供了无与伦比的非洲高级模块计划；世界上最迷人和最具挑战性的地区之一。对非洲大陆进行跨学科研究的机会是该学位的一个特殊优势。我们以前的学生出于各种原因选择在这个级别学习非洲。对于某些人对特定地区的历史和文化或政治经济的浓厚兴趣是足够的动力，但对于许多学生来说，伦敦大学亚非学院非洲研究文学硕士还旨在进一步扩大他们的职业机会。有些人继续在非洲或与非洲有关的领域工作。",
  "language_requirements": "{{ per_lang.name }}",
  "curriculum": "非洲研究论文 (Dissertation in African Studies)\n非洲现当代艺术 (Modern and Contemporary Arts in Africa)\n二十世纪南非的种族、隔离和种族隔离（PG） (Race, Segregation, and Apartheid in Twentieth-century South Africa (PG))\n亚洲、非洲和中东性别问题的历史观点 (Historical Perspectives on Gender in Asia, Africa and the Middle East)\n非洲哲学（PG） (African Philosophy (PG))\n当代非洲文学 (Contemporary African Literature (PG))\n非洲的语言、身份和社会 (Language, Identity and Society in Africa (PG))\n非洲政治 (The Politics of Africa)",
  "success_cases": ""
}