{
  "school_name": "伦敦大学玛丽皇后学院",
  "major_name": "心理健康：文化心理学与精神病学理学硕士",
  "ename": "MSc Mental Health: Cultural Psychology and Psychiatry",
  "tags": "社科,心理学,医学和牙科学院",
  "introduction": "专业方向: 心理学\n入学时间: 9月\n项目时长: 1年\n项目学费: 25500英镑/年",
  "requirements": "具有2:2荣誉学位或同等学历，需要心理学、医学或相关学科背景",
  "objectives": "伦敦大学玛丽皇后学院心理健康：文化心理学与精神病学理学硕士项目将深入探讨社会文化因素对精神健康、精神疾病和精神卫生保健的影响，特别文化在精神疾病诊断和提供不同的心理和精神治疗方法方面的作用。学生将了解心理健康问题的文化背景，了解跨文化提供护理的创新方式，并获得与来自不同文化背景的人合作的经验。",
  "language_requirements": "{{ per_lang.name }}",
  "curriculum": "论文 (Dissertation)\n语境中的心理健康 (Mental Health in Context)\n心理健康专业技能 (Professional Skills in Mental Health)\n应用研究方法1：理论 (Applied Research Methods 1: Theory)\n应用研究方法2：实践 (Applied Research Methods 2: Practice)\n文化心理学与精神病学：理论与方法 (Cultural Psychology and Psychiatry: Theory and Menthod)\n文化心理学与精神病学：临床应用 (Cultural Psychology and Psychiatry: Clinical Applications)",
  "success_cases": ""
}