{
  "school_name": "伦敦大学玛丽皇后学院",
  "major_name": "临床实践牙齿科学理学硕士",
  "ename": "MSc Dental Science for Clinical Practice",
  "tags": "社科,医学,医学和牙科学院",
  "introduction": "专业方向: 医学\n入学时间: 9月\n项目时长: 1年\n项目学费: 42250英镑/年",
  "requirements": "具有牙科相关专业背景，有至少一年的牙科全职工作经验",
  "objectives": "伦敦大学玛丽皇后学院临床实践牙齿科学理学硕士项目旨在为国际合格的牙科毕业生在英国实习做好准备。课程提供了六个关键培训领域的综合基础：基础科学及其在现代牙科实践中的应用、临床牙科应用原理、临床技能、沟通技巧、专业精神、管理和领导力。",
  "language_requirements": "{{ per_lang.name }}",
  "curriculum": "研究方法基础 (Fundamentals of Research Methods)\n临床牙科应用原理 (Applied Principles of Clinical Dentistry)\n临床牙科技能 (Clinical Dental Skills)\n职业化管理与领导 (Professionalism Management and Leadership)\n牙科人体模型实用技能 (Dental Manikin Practical Skills)\n牙科临床审计项目 (Dental Science Clinical Audit Project)",
  "success_cases": ""
}