{
  "school_name": "伦敦大学城市学院",
  "major_name": "言语与语言治疗理学硕士",
  "ename": "MSc Speech and Language Therapy",
  "tags": "社科,医学,健康与心理科学学院",
  "introduction": "专业方向: 医学\n入学时间: 9月\n项目时长: 2年\n项目学费: 21000英镑/年",
  "requirements": "具有2:1学士学位或同等学历\n至少五门GCSE科目达到Grade 4(C)或同等水平，包括英语和数学",
  "objectives": "伦敦大学城市学院言语与语言治疗理学硕士旨在增进对一些领域中典型的言语，语言，交流，吞咽和病理的理解",
  "language_requirements": "{{ per_lang.name }}",
  "curriculum": "语音，语音和语音发展 (Articulatory Phonetics, Phonology and Speech Development)\n生物医学科学 (Bio-medical Sciences)\n寿命跨度心理学与研究方法 (Life Span Psychology and Research Methods)\n语言障碍，不流畅性和扩张性 (Speech Disorders, Dysfluency and Augmentative and Alternative)\n吞咽困难，声音，运动言语障碍，痴呆 (Dysphagia, Voice, Motor Speech Disorders, Dementia)\n语言科学：语言学和语言发展 (Language Sciences: Linguistics and Language Development)\n专业研究A (Professional Studies A)\n循证实践和数据分析 (Evidence Based Practice and Data Analysis)\n声学，听觉和耳聋 (Acoustic Phonetics, Audiology and Deafness)\n获得性和发展性语言障碍 (Acquired and Developmental Language Disorders)\n自闭症谱系障碍，学习障碍，儿童心理健康，脑瘫，腭裂 (Autism Spectrum Disorder, Learning Disability, Child Mental Health, Cerebral Palsy, Cleft Palate)\n专业研究B (Professional Studies B)",
  "success_cases": ""
}