{
  "school_name": "伦敦大学学院",
  "major_name": "自然启发解决方案理学硕士",
  "ename": "MSc Nature-Inspired Solutions",
  "tags": "社科,其他社科,工程科学学院",
  "introduction": "专业方向: 其他社科\n入学时间: 9月\n项目时长: 1年\n项目学费: 39800英镑/年",
  "requirements": "具有英国大学颁发的2:1学士学位或同等学历，需要相关学科背景",
  "objectives": "伦敦大学学院自然灵感的解决方案理学硕士项目专门旨在让学生通过与研究相关的教学和公众参与，从自然中汲取灵感（例如弹性、可扩展性和效率）来解决跨学科问题，从而开发出变革性的解决方案。例如，在能源转型和环境可持续性的背景下，学生可以从人肺的可扩展性和效率中学习，重新设计氢燃料电池和二氧化碳电还原，以实现我们的净零排放。学生可以从肾脏的弹性和细胞膜的效率中学习，以开发卓越的水处理解决方案，并从树木和森林中学习如何在制造中实现循环。\n伦敦大学学院自然灵感的解决方案理学硕士项目涵盖广泛领域的创新系统设计方法，包括可持续制造、能源和环境技术、功能材料、健康和生物医学工程以及建筑环境，在紧迫的环境中迫切需要跳出框框的思维联合国可持续发展目标 (SDG) 的背景。\n此外，伦敦大学学院自然灵感的解决方案理学硕士项目让学生准备好学习如何在多学科团队中解决跨学科问题，为您提供可转移的横向思维技能和竞争优势，以从事研发、创业或行业的职业。\n伦敦大学学院自然灵感的解决方案理学硕士项目教育未来的毕业生在基于非常规问题解决和分析的创新和设计方面具有独特的资格，使用自然界提供的大量解决方案，无缝地跨越传统学科界限。",
  "language_requirements": "{{ per_lang.name }}",
  "curriculum": "受自然启发的解决方案 (Nature-Inspired Solutions)\n受自然启发的材料工程 (Nature-Inspired Materials Engineering)\n自然灵感设计 (Nature-Inspired Design)\n自然系统动力学 (Dynamics of Natural Systems)\n受自然启发的研究项目 (Nature-Inspired Research Project)\n研究方法（化学工程）1 (Research Methods (Chemical Engineering) 1)\n研究方法（化学工程）2 (Research Methods (Chemical Engineering) 2)\n可持续性和决策 (Sustainability and Decision-Making)\n工程系统的可持续性分析 (Sustainability Analysis of Engineering Systems)\n高级表征 (Advanced Characterisation)\n受自然启发的生物工程 (Nature-Inspired Bioengineering)\n工程系统的数学建模 (Mathematical Modelling of Engineering Systems)\n社区福祉、健康不平等和社会处方的作用 (Community Wellbeing, Health Inequalities and the role of Social Prescribing)\n公民科学基金会 (Foundations of Citizen Science)\n包容性设计和环境 (Inclusive Design and Environments)",
  "success_cases": ""
}