{
  "school_name": "伦敦大学亚非学院",
  "major_name": "南亚研究与强化语言文学硕士",
  "ename": "MA South Asian Studies and Intensive Language",
  "tags": "社科,语言,语言、文化和语言学学院",
  "introduction": "专业方向: 语言\n入学时间: 9月\n项目时长: 2年\n项目学费: 25320英镑/年",
  "requirements": "具有2:2或以上学位",
  "objectives": "伦敦大学亚非学院南亚研究与强化语言文学硕士项目面向对南亚有职业和学术兴趣的学生。课程为学生提供了在世界上最多样化和最重要的地区之一进行学习的特殊机会，学生有机会接受南亚语言（孟加拉语、印地语、乌尔都语和梵语）的强化培训，以及学习跨学科的一系列课程。",
  "language_requirements": "{{ per_lang.name }}",
  "curriculum": "语言、社会与沟通 (Language, Society and Communication)\n重新绘制区域研究：亚洲、非洲和中东 (Remapping Area Studies in Asia, Africa and the Middle East)\n当代南亚的文化政治 (Politics of Culture in Contemporary South Asia)\n海外暑期印地语强化课程 (Intensive Hindi Summer Abroad)\n海外暑期乌尔都语强化课程 (Intensive Urdu Summer Abroad)\n海外暑期梵语强化课程 (Intensive Sanskrit Summer Abroad)\n梵语 (Sanskrit Language)\n印地语 (Hindi Language)\n乌尔都语 (Urdu Language)\n字幕的概念与实践 (Concepts and Practice of Subtitling)\n非洲、亚洲或中东语言的定向阅读 (Directed Readings in an African, Asian, or Middle Eastern Language)\n瑜伽在古印度的起源和发展 (The Origins and Development of Yoga in Ancient India)\n南亚地区研究学位论文 (Dissertation in South Asian Area Studies)\n古印度的宗教 (The Religions of Ancient India)\n瑜伽和冥想：观点、背景和方法 (Yoga and Meditation: Perspectives, Context and Methodologies)",
  "success_cases": ""
}