{
  "school_name": "伦敦政治经济学院",
  "major_name": "政治学（全球政治）理学硕士",
  "ename": "MSc Political Science (Global Politics)",
  "tags": "社科,国际关系,政府学系",
  "introduction": "专业方向: 国际关系\n入学时间: 9月\n项目时长: 1年\n项目学费: 28900英镑/年",
  "requirements": "具有2:1荣誉学位或同等学历，不限专业背景",
  "objectives": "伦敦政治经济学院全球政治学理学硕士项目包括一门必修课—全球化政治学，它全面概述了全球秩序结构的变化，以及全球化对国家内部和国家之间各种政治因素的影响。此外，学生将从50多门与全球政治有关的课程中进行选择，并就自己选择的课题完成论文。\n通过伦敦政治经济学院全球政治学理学硕士项目，学生将为进一步的研究工作或在国家、国际或全球层面的教育事业、公共服务或私营部门工作做好准备。",
  "language_requirements": "{{ per_lang.name }}",
  "curriculum": "全球化政治 (The Politics of Globalization)\n环境问题和发展干预 (Environmental Problems and Development Interventions)\n全球环境治理 ( Global Environmental Governance)\n非洲发展 (African Development )\n复杂的突发事件 (Complex Emergencies)\n国际机构和后期发展 ( International Institutions and Late Development)\n人道主义管理 (Managing Humanitarianism)\n人类安全 (Human Security)\n定性社会科学的贝叶斯推理:案例研究推理的现代方法 (Bayesian Reasoning for Qualitative Social Science: A modern approach to case study inference)\n东亚和东南亚的经济发展 (Economic Development of East and Southeast Asia)\n19世纪和20世纪世界经济的发展和一体化 (The Development and Integration of the World Economy in the 19th and 20th Centuries )\n欧洲资本主义模式 (European Models of Capitalism)\n全球政治中的文化和安全 (Culture and Security in Global Politics)",
  "success_cases": ""
}