{
  "school_name": "伦敦大学国王学院",
  "major_name": "干细胞与再生疗法：从实验到市场理学硕士",
  "ename": "MSc Stem Cell & Regenerative Therapies: From Bench to Market",
  "tags": "社科,医学,生命科学与药学学院",
  "introduction": "专业方向: 医学\n入学时间: 9月\n项目时长: 1年\n项目学费: 47700英镑/年",
  "requirements": "具有2:1本科（荣誉）学士学位，需要医学学位（MBBS或同等学历）或2:1/第一学位是相关生物科学学科背景，非传统学历将根据个人情况进行考虑",
  "objectives": "伦敦大学国王学院干细胞与再生疗法：从实验到市场理学硕士课程将生物和医学科学与商业、法律和生物伦理学相结合。该课程旨在培养细胞治疗的生物学、商业和监管方面的专业知识及其在生物医学中的应用，使学生能够在细胞治疗或相关学科中从事以商业为基础的职业。",
  "language_requirements": "{{ per_lang.name }}",
  "curriculum": "干细胞在细胞治疗和再生医学 (Stem Cells in Cellular Therapies & Regenerative Medicine)\n免疫学中的细胞疗法 (Cellular Therapies in Immunology )\n细胞治疗的商业化 (Commercialisation of Cellular Therapy)\n临床药物开发 (Clinical Drug Development)\n关于细胞治疗业务策略发展的论文 (Dissertation on business strategy development for cellular therapy)",
  "success_cases": ""
}