{
  "school_name": "伯明翰大学",
  "major_name": "人机交互理学硕士",
  "ename": "MSc Human Computer Interaction",
  "tags": "工科,计算机,计算机科学学院",
  "introduction": "专业方向: 计算机\n入学时间: 9月\n项目时长: 1年\n项目学费: 36000英镑/年",
  "requirements": "具有2:1荣誉学位或同等学历，需要计算机科学背景",
  "objectives": "人机交互可能是计算机系统成功与否的最重要决定领域，同时也为创新和创意提供了良好的平台。在伯明翰大学开设的人机交互理学硕士项目中，学生将有机会接触到人机交互的基础理论、方法和实务，通过学习诸如机器人学、自然启发计算和安全等选修课程，拓宽研究面。该项目立足于世界级人机交互中心的研究，旨在使学生胜任研究领域、行业或商业领域的工作。",
  "language_requirements": "{{ per_lang.name }}",
  "curriculum": "项目 (Project )\nHCI研究课题 (Research Topics in HCI )\n移动和普适计算（扩展） (Mobile and Ubiquitous Computing (Extended) )\n人机交互理论与实践 (Human Compter Interaction Theory and Practice )\n小型项目 (Mini Project )\n研究技能、评估方法和统计 (Research Skills, Evaluation Methods, and Statistics)\n智能机器人（扩展） (Intelligent Robotics (Extended) )\n在教授计算机科学（扩展） (Teaching Computer Science in Schools (Extended))\n个别研究（扩展） (Individual Studies (Extended) )\n机器学习与智能数据分析（扩展） (Machine Learning and Intelligent Data Analysis (Extended))\n软件研讨会1 (Software Workshop 1 )\n软件研讨会2 (Software Workshop 2 )",
  "success_cases": ""
}