{
  "school_name": "兰卡斯特大学",
  "major_name": "政治学、哲学与管理理学硕士",
  "ename": "MSc Politics, Philosophy and Management",
  "tags": "社科,其他社科,组织、工作与技术学院",
  "introduction": "专业方向: 其他社科\n入学时间: 10月\n项目时长: 1年\n项目学费: 27300英镑/年",
  "requirements": "具有英国2:1荣誉学位或同等学历，需要管理学、商业研究、社会科学、历史学、哲学、英语、语言、艺术或其他人文学科背景，具备相关工作经验者优先考虑（但非必需）\n学校也可能考虑非标准申请者，需要联系学校获取信息",
  "objectives": "组织越来越多地寻找对管理的社会、政治和道德层面有更深刻理解的毕业生，以便他们能够保护社会的更广泛利益。兰卡斯特大学政治学、哲学与管理理学硕士项目满足了对一种新型管理毕业生的需求-能够驾驭更广泛的环境，并将哲学作为解决关键政治和社会问题的工具。该课程培养有能力的管理者，他们能看到复杂问题之间的潜在联系。这些人能够满足协调经济增长、可持续性和公平社会结果的需求。该课程确保毕业生适应当代政治发展和国际关系。学生将学习如何处理复杂问题，如人员管理和组织变革。学生将深入了解与政治、哲学和机构管理相关的主要历史和知识理论、概念和问题。除了这种全新的思维方式，学生还将获得和培养跨文化团队合作、谈判、研究设计和报告写作等技能。",
  "language_requirements": "{{ per_lang.name }}",
  "curriculum": "学位论文 (Dissertation)\n人力资源管理I：语境、争议和批评 (Human Resource Management I: Contexts、Controversies and Critiques)\n哲学是什么方法、目的、辩论 (What is Philosophy Methods、Aims、Debates)\n宗教研究 (Studying Religion)\n外交与外交政策的理论和概念 (Theory and Concepts in Diplomacy and Foreign Policy)\n国际关系研究的主要方法 (Major Approaches to the Study of International Relations)\n冲突管理与当代冲突 (Conflict Management and Contemporary Conflicts)\n二十一世纪的组织：当代世界组织的新形式 (Organisations in the 21st Century: New Forms of Organising in the Contemporary World)\n组织变革的管理：挑战与争论 (The Management of Organisational Change: Challenges and Debates)\n人力资源管理II：人力资源管理的兴起与发展 (Human Resource Management II: The rise and growth of HRM)",
  "success_cases": ""
}