{
  "school_name": "卡迪夫大学",
  "major_name": "社会科学研究方法理学硕士（国际关系）",
  "ename": "MSc Social Science Research Methods (International Relations)",
  "tags": "社科,国际关系,法律与政治学院",
  "introduction": "专业方向: 国际关系\n入学时间: 9月\n项目时长: 1年\n项目学费: 24950英镑/年",
  "requirements": "具有2:2荣誉学位或同等学历，需要相关学科领域背景，如区域研究、犯罪学、批判心理学、教育、地理、历史、工业和员工关系、法律、管理和商业研究、教育学、政治、公共管理、社会政策和社会工作或社会学\n如果申请者没有相关领域的学位，学校会考虑相关专业经验，需要提交其他证据支持",
  "objectives": "卡迪夫大学社会科学研究方法理学硕士（国际关系）项目提供高级社会科学研究方法训练，培养学生分析能力、夯实跨学科知识基础、开展多样的国际关系实践研究活动。学生将深入学习研究方法的理论与实践知识，探索社会科学研究数据收集方法与主要的分析方法。",
  "language_requirements": "{{ per_lang.name }}",
  "curriculum": "学位论文 (Dissertation)\n核心研究技能培养 (Developing Core Research Skills)\n社会科学研究基础 (Foundations of Social Science Research)\n定性研究方法 (Qualitative Research Methods)\n定量研究方法 (Quantitative Research Methods)\n研究运用 (Research Applications)",
  "success_cases": ""
}