{
  "school_name": "卡迪夫大学",
  "major_name": "数字媒体与社会文学硕士",
  "ename": "MA Digital Media and Society",
  "tags": "社科,新媒体,新闻、媒体与文化学院",
  "introduction": "专业方向: 新媒体\n入学时间: 9月\n项目时长: 1年\n项目学费: 23700英镑/年",
  "requirements": "具有2:2荣誉学位或同等学历，具备相关学科背景，如艺术、人文或社会科学，或者有相关工作经验也会被考虑",
  "objectives": "卡迪夫大学数字媒体与社会文学硕士项目研究当前网络传播与互联网研究的问题与挑战，帮助学生深入学习社交媒体、大数据、公民新闻、数字文化、创意产业、网络治理等专业知识，夯实媒体与传播理论与方法论知识基础。学生将深入探究当前媒体的数字化转化，提高对于社会、政治、经济背景中数字媒体的分析能力，探讨网络用户、国家与经济活动如何塑造网络传播，以及反过来数字媒体如何影响我们的社会。",
  "language_requirements": "{{ per_lang.name }}",
  "curriculum": "项目论文 (Project Based Dissertation)\n研究实践1 (Putting Research into Practice 1)\n研究实践2 (Putting Research into Practice 2)\n理解数字媒体 (Understanding Digital Media)\n公民新闻与数字公众 (Citizen Journalism and Digital Publics)\n媒体与传播的争论和概念 (Debates and Concepts in Media and Communications)",
  "success_cases": ""
}