{
  "school_name": "圣安德鲁斯大学",
  "major_name": "能源政策与金融理学硕士",
  "ename": "MSc Energy Policy and Finance",
  "tags": "工科,能源,跨学科研究学院",
  "introduction": "专业方向: 能源\n入学时间: 9月\n项目时长: 1年\n项目学费: 29990英镑/年",
  "requirements": "具有2:1学位或同等学历，学科背景可包括但不限于：政治学、公共政策、社会学、地理学、管理学、工程学、经济与金融、商学、国际关系、人类学。申请者应具备良好的计算能力",
  "objectives": "为我们所有人创造更美好能源未来的挑战既紧迫又复杂。圣安德鲁斯大学能源政策与金融理学硕士项目专为匹配和解决这种复杂性而设计。它汇集了来自艺术、人文、社会和自然科学领域的学术专家，以提供对全球、国家和地方能源挑战的深入、跨学科的理解。强调实践技能的发展，并让来自政策、工业和金融领域的外部合作伙伴参与进来，圣安德鲁斯大学能源政策与金融理学硕士提供的不仅仅是学术资格。它为学生提供知识和能力，使他们能够在学术界内外定义和追求能源领域新的和多样化的职业轨迹。",
  "language_requirements": "{{ per_lang.name }}",
  "curriculum": "能源不平等与气候责任 (Energy Inequalities and Climate Responsibilities)\n能源科学 (Energy Sciences)\n能源金融与政策 (Energy Finance and Policy)\n能源人文 (Energy Humanities)\n论文项目 (Dissertation Project)",
  "success_cases": ""
}