{
  "school_name": "圣安德鲁斯大学",
  "major_name": "近代早期与改革史文学硕士",
  "ename": "MLitt Early Modern and Reformation History",
  "tags": "社科,历史,历史学院",
  "introduction": "专业方向: 历史\n入学时间: 9月\n项目时长: 1年\n项目学费: 25900英镑/年",
  "requirements": "具有2:1学位或同等学历，需要相关学科领域背景，需要1篇 written work（2,000 words)",
  "objectives": "圣安德鲁斯大学近代早期和改革史文学硕士项目提供对早期现代欧洲和大西洋世界（包括奥斯曼帝国）历史的深入研究。发现一系列研究早期现代历史（1450 年至 1750 年）的方法，并获得研究该时期所需的技能。学生也可以选择专攻早期现代宗教史。\n圣安德鲁斯大学近代早期和改革史文学硕士项目与大量早期现代史学者合作，他们可以在早期现代欧洲和大西洋世界的政治、社会和文化历史方面提供高水平的专业监督和高级培训。对于那些选择专攻改革历史的学生，该课程灌输了对所有欧洲改革的广泛背景意识，同时也提供了对特定神学、地理或方法论领域进行详细研究的机会。受益于广泛而深入的准备，让您有机会探索和批判性地评估史学和主要来源。追求高水平的技能培训，以建立您的 MLitt 论文。为对后续博士研究感兴趣的学生做准备。",
  "language_requirements": "{{ per_lang.name }}",
  "curriculum": "近代早期历史的主题和辩论 (Themes and Debates in Early Modern History)\n改革方面 (Aspects of Reformation)\n早期现代文件和资料 (Early Modern Documents and Sources)\n研究生研究用拉丁语 (Latin for Postgraduate Research)\n材料书目 (Material Bibliography)\n古文字学和手稿研究 (Paleography and Manuscript Studies)\n历史导读 (Directed Reading in History)\n欧洲文艺复兴 (The European Renaissance)\n政治思想和思想史 (Political Thought and Intellectual History)\n早期现代英国的宗教和身份 (Religion and Identity in Early Modern Britain)\n现代早期欧洲和新世界的战争、国家和社会 (War, State and Society in Early Modern Europe and New Worlds)",
  "success_cases": ""
}