{
  "school_name": "埃克塞特大学",
  "major_name": "可持续商业管理理学硕士",
  "ename": "MSc Sustainable Business Management",
  "tags": "商科,管理,商学院",
  "introduction": "专业方向: 管理\n入学时间: 9月\n项目时长: 1年\n项目学费: 30700英镑/年",
  "requirements": "具有2:2荣誉学位或同等学历，学校会考虑所有有证据表明在与学习计划相关的课程中表现优异、有丰富的相关工作经验或专业资格的申请",
  "objectives": "埃克塞特大学可持续商业管理理学硕士旨在培养学生高级商业技能，结合对可持续性的深入理解以及商业在创造可持续未来中的作用，同时研究一系列跨学科的模块，如气候变化、政策和治理、环境和人类健康，由专家教授最紧迫的可持续性问题及其解决方案，学生可以参与有关仿生学和循环经济的最新概念和辩论，最后可以在所有市场部门的一般管理或领导职位或在环境和可持续发展方面担任更多专业职位的职业发展。",
  "language_requirements": "{{ per_lang.name }}",
  "curriculum": "可持续经营管理\t (Sustainable Business Management)\n可持续业务的战略创新\t (Strategic Innovation for Sustainable Business)\n主要项目 (Major Project)\n循环经济管理咨询服务 (Circular Economy Management Consultancy Services)\n业务转型案例研究 (Business Transformation Case Study)\n仿生学与循环经济设计原则 (Biomimicry and Circular Economy Design Principles)\n环境治理 (Environmental Governance)\n当代旅游业 (Contemporary Tourism Industry)\n可持续旅游管理 (Sustainable Tourism Management)\n可持续发展的观点 (Perspectives on Sustainable Development)\n气候变化主题 (Themes in Climate Change)\n海洋和沿海社会生态系统 (Marine and Coastal Social-ecological Systems)\n自然、健康和福祉 (Nature, Health and Wellbeing)\n环境科学与人口健康 (Environmental Science and Population Health)\n全球公共卫生与环境变化 (Global Public Health and Environmental Change)\n当代环境与人类健康 (Contemporary Environment and Human Health)",
  "success_cases": ""
}