{
  "school_name": "威斯敏斯特大学",
  "major_name": "建筑与环境设计理学硕士",
  "ename": "MSc Architecture and Environmental Design",
  "tags": "社科,建筑,建筑与城市学院",
  "introduction": "专业方向: 建筑\n入学时间: 9月\n项目时长: 1年\n项目学费: 15500英镑/年",
  "requirements": "具有2:2荣誉学位，需要在建筑学，或建筑行业和建筑环境学科背景下的相关学科中拥有良好的作品集学校鼓励具有与项目相关的其他学科资格的申请者申请，每个申请都将根据成绩被考虑\n需要提交一份作品集，或一份相关经验的综合书面描述",
  "objectives": "威斯敏斯特大学建筑与环境设计理学硕士项目旨在为学生提供可以应用于多种建筑类型和全球气候、环境和上下文问题的技能。完成本课程后，学生将全面了解环境设计的原理和方法论，并培养批判性思维技能，挑战现有的实践。掌握知识和实用工具，以更好地理解现有建筑，进行改造和设计新的建筑——积极推动这一领域的变化，并向真正具有环保意识的建筑迈进。威斯敏斯特大学建筑与环境设计理学硕士课程涵盖了环境设计的更广泛的背景和可持续方法，以及环保和能源意识建筑设计和性能的更多技术方面。除了授课模块外，学生还将学习基于设计的模块，在这些模块中，把定量和定性分析应用到现有的建筑环境和新的设计项目的研究中。这包括与健康和福祉相关方面的量化方法，如空气质量和建筑环境之间的关系。",
  "language_requirements": "{{ per_lang.name }}",
  "curriculum": "后碳文化 (Post-Carbon Culture)\n环境设计基础 (Fundamentals of Environmental Design)\n气候积极型环境 (Climate Positive Environments)\n循证环境建筑 (Evidence-Based Environmental Architecture)\n论文项目 (Thesis Project)\n论文主题 (Thesis Topic)\n能源与碳排放 (Energy and Carbon)",
  "success_cases": ""
}