{
  "school_name": "思克莱德大学",
  "major_name": "职业心理学理学硕士",
  "ename": "MSc Occupational Psychology",
  "tags": "社科,心理学,心理科学与健康学院",
  "introduction": "专业方向: 心理学\n入学时间: 9月\n项目时长: 1年\n项目学费: 29350英镑/年",
  "requirements": "具有二等荣誉学位，需要心理学背景。具有较低学位和可证明的工作经验的申请人将根据个人基础考虑",
  "objectives": "思克莱德大学职业心理学理学硕士项目涵盖工作和职业心理学的七个核心知识领域：工作心理评估；学习、培训和发展；领导力、参与度和激励；幸福与工作；工作设计、组织变革和发展；将心理学应用于工作组织；研究设计、先进的数据收集和分析技术。跨学科选修课还允许学生选择专业课程，例如数据科学、健康分析和人力资源管理/组织发展。",
  "language_requirements": "{{ per_lang.name }}",
  "curriculum": "工作评估与选择 (Assessment & Selection at Work)\n工作、健康与福祉 (Work, Health & Wellbeing)\n人才培养 (Developing Talent)\n领导力、参与度和动机 (Leadership, Engagement & Motivation)\n组织发展与变革 (Organisational Development & Change)\n人员分析与专业实践（咨询） (People Analytics & Professional Practice (Consultancy))\n量化研究方法 (Quantitative Research Methods)\n定性研究方法 (Qualitative Research Methods)\n人、技术与工作 (People, Technology & Work)\n人员分析与专业实践（基础） (People Analytics & Professional Practice (Foundations))\n商业环境下的人力资源管理 (HRM in a Business Context)\n当代雇佣关系 (Contemporary Employment Relations)\n全球背景下的劳动和多样性 (Labour and Diversity in a Global Context)\n人力资源管理的关键问题 (Critical Issues in HRM)\n可用卫生系统的设计 (Design of Usable Health Systems)\n健康、护理数据分析与决策支持 (Health & Care Data Analytics & Decision Support)\n商业分析 (Business Analytics)\n大数据基础 (Big Data Fundamentals)",
  "success_cases": ""
}