{
  "school_name": "爱丁堡大学",
  "major_name": "国际人力资源管理理学硕士",
  "ename": "MSc International Human Resource Management",
  "tags": "商科,人力资源管理,商学院",
  "introduction": "专业方向: 人力资源管理\n入学时间: 9月\n项目时长: 1年\n项目学费: 31600英镑/年",
  "requirements": "具有英国一等或2:1荣誉学位或同等学历，不限专业背景\n申请者必须表现出对从事人力资源管理工作的兴趣",
  "objectives": "爱丁堡大学国际人力资源管理理学硕士学位课程旨在为学生提供人力资源管理从业人员在全球组织中工作所需的知识和技能。\n通过爱丁堡大学国际人力资源管理理学硕士学位课程的学习，学生将：\n理解国际人力资源管理领域的关键术语、理论、概念和实践；\n从选修课中深入学习关于国际人力资源管理具体的理论、技能和实践；\n认识到日益加剧的全球化对人类资源管理，尤其是跨国公司的国际人力资源管理可能产生的影响；\n培养开展定性、定量分析研究的能力，并将其运用到诸如论文的独立作业中；\n辨别和认识伦理道德问题在人力资源实践以及职场人员管理中的重要性。",
  "language_requirements": "{{ per_lang.name }}",
  "curriculum": "国际人力资源管理政策和实践 (International HRM Policies and Practices)\n组织行为学 (Organisational Behaviours)\n奖励管理 (Reward Management)\n人力资源专业人员的核心竞争力 (Core Competencies for HR Professionals)\n人力资源管理研究方法 (Methods of Research in HRM)\n跨国企业与比较雇佣关系 (Multinational Enterprises & Comparative Employment Relations)\n就业法 (Employment Law)\n绩效管理 (Performance Management)\n领导力与管理发展 (Leadership and Management Development)\n外包人力资源议题 (HR Issues in Outsourcing)\n全球人才管理 (Global Talent Management)",
  "success_cases": ""
}