{
  "school_name": "纽卡斯尔大学（英国）",
  "major_name": "跨文化交际文学硕士",
  "ename": "MA Cross-Cultural Communication",
  "tags": "社科,教育,教育、交流与语言科学学院",
  "introduction": "专业方向: 教育\n入学时间: 9月\n项目时长: 1年\n项目学费: 25100英镑/年",
  "requirements": "具有2:1荣誉学位或同等学历，需要以下学科背景：人类学，传播学，民族志，跨文化交际，国际关系，语言学，哲学，心理学，政治学，社会人类学，社会心理学，社会学，TESOL，现代外语，翻译\n学校也会考虑以下学科并具备相关工作经验（例如在国际组织或跨文化背景下）的毕业生：教育，区域研究，英语，地理，历史，法律\n学校可能会考虑以下情况的申请者：任意其他学科并具备相关工作经验（例如在国际组织或跨文化背景下）的毕业生，或具有较低或非标准资格并具备相关工作经验（例如在国际组织或跨文化背景下）的申请者",
  "objectives": "纽卡斯尔大学跨文化交际文学硕士项目迎合了世界上日益增长的跨文化交际需求，为学生提供以交际为中心的培训，旨在发展学生跨文化交际方面的专业知识，课程内容涵盖文化与人类行为之间的互相联系等方面。",
  "language_requirements": "{{ per_lang.name }}",
  "curriculum": "研究计划 (Research Portfolio)\n语言和跨文化交流 (Language and Cross-Cultural Communication)\n交际的社会心理学 (The Social Psychology of Communication)\n社会语言学 (Sociolinguistics)\n国际商务洽谈与互动 (International Business Talk and Interaction)\n专业交际 (Professional Communication)\n文化、跨文化和身份认同 (Culture、Interculturality and Identity)\n交互分析导论 (Introduction to Interaction Analysis)\n了解多渠道交际 (Understanding Multimodal Communication)\n世界英语：英语作为通用语的全球和跨文化问题 (English in the World: Global and Cross-Cultural Issues surrounding English as a Lingua Franca)",
  "success_cases": ""
}