{
  "school_name": "纽卡斯尔大学（英国）",
  "major_name": "博物馆研究文学硕士",
  "ename": "MA Museum Studies",
  "tags": "社科,文化,艺术和文化学院",
  "introduction": "专业方向: 文化\n入学时间: 9月\n项目时长: 1年\n项目学费: 25100英镑/年",
  "requirements": "具有2:1荣誉学位或同等学历，不限专业背景\n学校也会考虑具有非标准资格和/或在博物馆、画廊及文物领域具备相关工作经验的申请者\n申请者可能需要参加面试",
  "objectives": "纽卡斯尔大学博物馆研究文学硕士项目将培养学生经营一家博物馆所需的实用技能，同时为学生提供有关博物馆作为社会角色的理论知识。学生将通过策划集体展览或在知名公共场所举办复杂的教育和学习活动获得经验并培养竞争优势。",
  "language_requirements": "{{ per_lang.name }}",
  "curriculum": "了解博物馆/美术馆/文化遗产研究中的挑战 (Understanding Challenges in Museum/Gallery/Heritage Studies )\n博物馆/美术馆/文化遗产部门的“藏品”护理 (Caring for 'Collections' in the Museum/Gallery/Heritage Sector )\n在博物馆/美术馆/文化遗产研究中交流和学习 (Communicating and Learning in Museum/Gallery/Heritage Studies )\n管理博物馆/美术馆/文化遗产项目 (Managing Projects in the Museum/Gallery/Heritage Sector )\n了解博物馆/美术馆/文化遗产研究中的学术和应用研究 (Understanding Academic and Applied Research in Museum/Gallery/Heritage Studies)\n博物馆项目 (Working on a Project in the Museums Sector)\n博物馆/美术馆/文化遗产部门实践 (Museum/Gallery/Heritage Practice)\n研究论文写作 (Research Dissertation)\n职业导向项目研究 (Research – Vocationally-Orientated Project )\n博物馆、美术馆、文化遗产专业实践和研究 (Museum、Gallery、Heritage Professional Practice and Research)",
  "success_cases": ""
}