{
  "school_name": "考文垂大学",
  "major_name": "灾害管理与恢复理学硕士",
  "ename": "MSc Disaster Management and Resilience",
  "tags": "社科,其他社科,工程、环境与计算学院",
  "introduction": "专业方向: 其他社科\n入学时间: 1/5/9月\n项目时长: 1年\n项目学费: 18600英镑/年",
  "requirements": "具有2:2荣誉学位，需要相关学科背景。 学位较低和/或仅有专业经验的申请人将被单独考虑，并且通常会在获得课程名额之前进行面试",
  "objectives": "考文垂大学灾害管理与恢复理学硕士项目旨在为希望在灾害管理和人道主义行动方面开始职业生涯，或目前在地方或国家政府灾害管理机构、非政府组织或民间社会组织工作并且需要进一步发展职业生涯的学生提供所需的高级技能和知识，为学生提供发展知识和实践技能的机会，以识别、批判性分析、评估和成功地管理日益复杂的灾害，在政策制定、战略实施和响应管理方面自信地运作。总体目标是使学生能够为加强社区、专业、组织、国家和国际能力作出贡献，以应对复杂的多因素灾害，制定战略，提高对经济和社会面临的急性和慢性威胁的恢复力。",
  "language_requirements": "{{ per_lang.name }}",
  "curriculum": "灾害风险、恢复、适应与可持续性 (Disaster Risk, Resilience, Adaptation and Sustainability)\n培训和练习的设计与交付 (Training and Exercise Design and Delivery)\n弹性、安全与新兴技术 (Resilience, Security and Emerging Technologies)\n社区准备、恢复与复原力 (Community Preparedness, Recovery and Resilience)\n人道主义原则，准备与响应 (Humanitarian Principles, Preparedness and Response)\n灾害干预、评估与学习 (Disaster Interventions, Evaluation and Learning)\n风险，事件与领导力 (Risk, Incident and Leadership)\n研究观点与实践 (Research Perspectives and Practice)\n支持过渡到研究生学习 (Supporting Transition to Postgraduate Study)\n准备研究 (Preparing to Research)\n工作论文 (Working paper)",
  "success_cases": ""
}