{
  "school_name": "诺丁汉大学",
  "major_name": "健康心理学理学硕士",
  "ename": "MSc Health Psychology",
  "tags": "社科,心理学,医学院",
  "introduction": "专业方向: 心理学\n入学时间: 9月\n项目时长: 1年\n项目学费: 27150英镑/年",
  "requirements": "具有2:1学位或同等学历，需要心理学背景\n申请者需要从其大学或英国心理学会（BPS）获得GBC资格证明\n如果申请者在英国以外的机构完成了学位，需要提交1份英国心理学会研究生会员资格的个人申请，以便被正确地评估是否有资格获得GBC",
  "objectives": "诺丁汉大学健康心理学硕士项目创立于2003年，由英国心理学会(BPS)批准，可认证特许心理学家。学生可参加全日制或非全日制的学习。诺丁汉大学健康心理学硕士项目适合那些希望成为职业健康心理学家的人，也适合对伴随着身体健康的心理因素感兴趣的人。健康心理学家的职业选择正在增多，英国国家医疗服务体系、工业和学术机构都提供了就业机会。",
  "language_requirements": "{{ per_lang.name }}",
  "curriculum": "健康心理学的背景和观点 (Context and Perspectives in Health Psychology)\n研究方法介绍 (Introduction in Research Methods)\n了解、预测和改变健康行为 (Understanding、Predicting and Changing Health Behaviour)\n慢性病 (Chronic Illness)\n卫生保健环境 (Health Care Contexts)\n健康心理学的专业技能 (Professional Skills in Health Psychology)\n定性研究方法 (Qualitative Research Methods)\n定量方法 (Quantitative Methods)",
  "success_cases": ""
}