{
  "school_name": "诺丁汉大学",
  "major_name": "发育障碍理学硕士",
  "ename": "MSc Developmental Disorders",
  "tags": "社科,心理学,心理学院",
  "introduction": "专业方向: 心理学\n入学时间: 9月\n项目时长: 1年\n项目学费: 30750英镑/年",
  "requirements": "具有2:1学位或同等学历，需要BPS认可的心理学学位，持有非BPS认可的心理学学士学位的申请者可能会被录取，前提是其成绩单中包含心理学研究方法和统计学课程",
  "objectives": "诺丁汉大学发育障碍理学硕士项目加深学生对各种疾病的理解，包括自闭症、智力障碍和儿童精神疾病。通过参与高级理论和实践工作，学生将了解：研究方法、诊断和评估、治疗和教育干预。",
  "language_requirements": "{{ per_lang.name }}",
  "curriculum": "专业技能 - 发育障碍理学硕士 (Professional Skills - Developmental Disorders MSc)\n发育障碍的背景 (Developmental Disorders in Context)\n神经发育障碍 (Neurodevelopmental Disorders)\n心理评估 (Psychological Assessment)\n心理学高级方法 (Advanced Methods in Psychology)\n儿童临床和行为障碍 (Childhood Clinical and Behavioural Disorders)\n研究项目 (Research Project)",
  "success_cases": ""
}