{
  "school_name": "贝尔法斯特女王大学",
  "major_name": "哲学文学硕士",
  "ename": "MA Philosophy",
  "tags": "社科,哲学,历史、人类学、哲学和政治学院",
  "introduction": "专业方向: 哲学\n入学时间: 9月\n项目时长: 1年\n项目学费: 21500英镑/年",
  "requirements": "通常具有strong 2:2荣誉学位（至少55%）或学校接受的同等学历，需要社会科学、人文或艺术学科背景；或具有2:2荣誉学位（至少55%）或学校接受的同等学历，不限专业背景，并且具备相关专业经验。",
  "objectives": "贝尔法斯特女王大学哲学文学硕士项目是一个多元化项目，承认并重视不同的哲学方法、历史和学术方法，同时为学生提供哲学核心领域的坚实基础。学生的体验是通才硕士课程的体验，通过对学科历史的包容性方法以及对二十一世纪问题和辩论的参与来提供信息。学生将探索历史和当代的辩论，解决抽象和具体问题，并回答基本和应用问题。\n学生将与国际公认的哲学研究领袖一起学习。我们的员工在伦理学和认识论以及科学哲学、形而上学、宗教哲学、技术哲学、政治哲学和后康德欧洲哲学方面具有优势。在比较和多样化的全球哲学传统方面的专业知识不断增长。以研究为主导的教学让学生作为积极参与者进入前沿研究，我们充满活力的研究社区为学生提供了多种机会来追求有意义的研究经历。\n哲学硕士学生有机会通过论文和单独协商的主题模块来个性化他们的教育。在导师的指导下，学生可以选择一个他们感兴趣的主题，与一个小组进行定向批判性阅读和分析。学生还受益于 AHSS 学院和学院内广泛的跨学科机会，以及女王大学优秀的研究生体验基础设施。学生可以选择在 QUB 完成战略领导。",
  "language_requirements": "{{ per_lang.name }}",
  "curriculum": "研究设计方法 (Approaches to Research Design)\n应用哲学 (Applied Philosophy)\n哲学论文 (Philosophy Dissertation)\n习惯与成瘾的哲学 (Philosophies of Habit and Addiction)\n知识与无知 (Knowledge and Ignorance)\n单独协商主题 (Individually Negotiated Topic)\n社会不公正 (Social Injustice)\n全球哲学史 (Global Histories of Philosophy)\n道德、法律和责任 (Ethics, Law, and Responsibility)",
  "success_cases": ""
}