{
  "school_name": "邓迪大学",
  "major_name": "土木工程与海洋可再生能源理学硕士",
  "ename": "MSc Civil Engineering with Marine Renewable Energy",
  "tags": "工科,海洋技术,理工学院",
  "introduction": "专业方向: 海洋技术\n入学时间: 1/9月\n项目时长: 1年\n项目学费: 27900英镑/年",
  "requirements": "具有2:2学位或同等学历，需要相关学科背景或有适当的专业经验",
  "objectives": "邓迪大学土木工程与海洋可再生能源理学硕士项目是一门工程学科，专注于构成现代社会的基础设施的设计、施工和维护。这包括道路、桥梁、建筑物和供水系统等广泛的项目。海洋可再生能源是利用潮汐、波浪和洋流等海洋资源发电的过程。它通过捕获海洋自然运动产生的能量来提供可持续的清洁电力。\n以海洋可再生能源为重点的土木工程将土木工程原理与海洋可再生能源的勘探和利用相结合。这一专业领域涉及专门用于利用海洋​​能源的结构和系统的设计和开发，特别是通过捕获潮汐和波浪能的技术。",
  "language_requirements": "{{ per_lang.name }}",
  "curriculum": "海洋可再生能源与设计 (Marine Renewable Energy & Design)\n流体动力学和海洋工程 (Hydrodynamics & Ocean Engineering)\n健康、安全和环境管理 (Health and Safety and Environmental Management)\n概念设计 (Conceptual Design)\n生命周期分析与环境影响评价 (Life Cycle Analysis & Environmental Impact Assessment)\n海洋岩土工程1 (Offshore Geotechnical Engineering I)\n专业发展 (Professional Development)\n硕士土木工程研究项目 (MSc Civil Engineering Research Project)\n结构分析基础 (Fundamentals of Structural Analysis)\n流体力学基础 (Fundamentals of Fluid Mechanics)\n土力学基础 (Fundamentals of Soil Mechanics)\n土动力学 (Soil Dynamics)\n项目管理团队 (Project Management Teams)\n结构动力学与地震工程 (Structural Dynamics and Earthquake Engineering)\n工作学习I (Work-based learning I)\n工作学习III (Work-based learning III)\n高级海洋岩土工程 (Advanced Offshore Geotechnical Engineering )\n有限元建模 (Finite Element Modelling)\n项目管理系统  (Project Management Systems)\n工作学习II (Work-based learning II)",
  "success_cases": ""
}