{
  "school_name": "雷丁大学",
  "major_name": "发展金融理学硕士",
  "ename": "MSc Development Finance",
  "tags": "商科,金融,农业、政策与发展学院",
  "introduction": "专业方向: 金融\n入学时间: 9月\n项目时长: 1年\n项目学费: 25850英镑/年",
  "requirements": "具有high 2:2或以上学位。学校欢迎有相关职业经验的申请者申请申请者的本科学位应该包括经济学、会计或金融的重要元素。 没有或很少接受经济学培训的优秀申请者，如果参加了学前经济学课程，则可能会被学校录取",
  "objectives": "雷丁大学发展金融理学硕士学位课程涉及研究正式及非正式金融部门、推广普惠金融的政策、顾客金融服务需求、制度设计和金融改革。\n雷丁大学发展金融理学硕士学位的核心课程以发展和宏观经济政策的主要观点为背景，涵盖了发展金融和微型企业金融领域的关键议题。选修课程使学生有机会深入研究金融服务部门专业领域，以及（或）探索其他一系列与发展相关的话题。",
  "language_requirements": "{{ per_lang.name }}",
  "curriculum": "发展金融学 (Development Finance)\n小额信贷 (Microfinance)\n农业和农村发展项目评估 (Appraisal of Agricultural and Rural Development Projects)\n发展中国家宏观经济学 (Macroeconomics for Developing Countries )\n自主学习研究和学习技巧 (Research and Study Skills for Independent Learning)",
  "success_cases": ""
}