{
  "school_name": "南洋理工大学",
  "major_name": "教育学硕士（马来语）",
  "ename": "Master of Education (Malay Language)",
  "tags": "社科,教育,教育学院",
  "introduction": "专业方向: 教育\n入学时间: 1月\n项目时长: 1年\n项目学费: 41900新币/年",
  "requirements": "具有认可大学颁发的良好学士学位，或具有相关的南洋理工大学FlexiMasters且成绩优秀\n具有教师资格如新加坡国立教育学院颁发的教育研究生文凭，或具备至少1年教育相关工作经验",
  "objectives": "教育学硕士课程主要面向在新加坡学校和教育部工作的教育工作者，学校也欢迎具有教育背景并希望提升教育知识和技能的大学毕业生申请。南洋理工大学教育学硕士（马来语）项目旨在为教育专业人员提供马来语教育的功能综合学术、实验和实地研究，该课程在社会文化背景下调查马来语言、文学和文化的研究理论和方法，将与马来语言课程开发和学校教学法的当前实践和进展一起提供，提供马来语和马来文学与文化研究的理论基础，以及调查这些领域与语言教学和学习的交集的机会，提高了教师和其他语言教育专业人员的研究技能和知识基础。",
  "language_requirements": "{{ per_lang.name }}",
  "curriculum": "教育调查 (Educational Inquiry)\n语言教育研究 (Research in Language Education)\n批判性与创造性思维促进学习 (Critical and Creative Thinking to Enhance Learning)\n文学教育 ( Literature Education)\n新加坡马来语的特点 (Features of the Malay Language in Singapore)\n马来语教学校本课程设计 ( School-based Curriculum Design for Malay Language Teaching)\n马来语和伊斯兰传统教育 (Education in Malay and Islamic Traditions)\n语言、识字与文化 (Language, Literacy and Culture)\n文学批评与理论 (Literary Criticism and Theories)\n语法理论 (Theories of Grammar)\n双语制和多语制 ( Bilingualism and Multilingualism)\n马来文化与价值观 (Malay Culture and Values)\n马来人的社会文化史 (The socio-cultural History of the Malays)\n语言批判方法 (Critical Approaches to Language)\n利用儿童与青少年文学促进社会情感学习 (Using Children and Young Adult Literature to Promote Social Emotional Learning)\n马来语课堂学习评估 (Assessment for Learning in Malay Language Classroom)",
  "success_cases": ""
}